mighty/VERSION
mighty/__init__.py
mighty/loss/__init__.py
mighty/loss/contrastive.py
mighty/loss/penalty.py
mighty/loss/triplet.py
mighty/models/__init__.py
mighty/models/autoencoder.py
mighty/models/flatten.py
mighty/models/mlp.py
mighty/models/serialize.py
mighty/monitor/__init__.py
mighty/monitor/accuracy.py
mighty/monitor/batch_timer.py
mighty/monitor/monitor.py
mighty/monitor/viz.py
mighty/monitor/mutual_info/__init__.py
mighty/monitor/mutual_info/_pca_preprocess.py
mighty/monitor/mutual_info/gcmi.py
mighty/monitor/mutual_info/idtxl.py
mighty/monitor/mutual_info/kmeans.py
mighty/monitor/mutual_info/mutual_info.py
mighty/monitor/mutual_info/neural_estimation.py
mighty/monitor/mutual_info/npeet.py
mighty/monitor/mutual_info/stub.py
mighty/tests/test_loss.py
mighty/tests/test_mask.py
mighty/tests/test_models.py
mighty/tests/test_mutual_info.py
mighty/tests/test_trainer.py
mighty/tests/test_utils.py
mighty/tests/test_utils_data.py
mighty/tests/test_var_online.py
mighty/trainer/__init__.py
mighty/trainer/autoencoder.py
mighty/trainer/embedding.py
mighty/trainer/gradient.py
mighty/trainer/mask.py
mighty/trainer/test.py
mighty/trainer/trainer.py
mighty/utils/__init__.py
mighty/utils/common.py
mighty/utils/constants.py
mighty/utils/domain.py
mighty/utils/hooks.py
mighty/utils/optimizer.py
mighty/utils/prepare.py
mighty/utils/signal.py
mighty/utils/stub.py
mighty/utils/var_online.py
mighty/utils/data/__init__.py
mighty/utils/data/loader.py
mighty/utils/data/normalize.py
mighty/utils/data/transforms_default.py
pytorch_mighty-0.4.0.dist-info/LICENSE
pytorch_mighty-0.4.0.dist-info/METADATA
pytorch_mighty-0.4.0.dist-info/WHEEL
pytorch_mighty-0.4.0.dist-info/top_level.txt
pytorch_mighty-0.4.0.dist-info/RECORD
