Metadata-Version: 2.1
Name: pytorch-mighty
Version: 0.4.0
Summary: The Mighty Monitor Trainer for your pytorch models.
Home-page: https://github.com/dizcza/pytorch-mighty
Author: Danylo Ulianych
Author-email: d.ulianych@gmail.com
License: BSD-3
Classifier: Intended Audience :: Developers
Classifier: Intended Audience :: Education
Classifier: Intended Audience :: Science/Research
Classifier: License :: OSI Approved :: BSD License
Classifier: Natural Language :: English
Classifier: Operating System :: OS Independent
Classifier: Programming Language :: Python :: 3
Classifier: Topic :: Scientific/Engineering
Classifier: Topic :: Scientific/Engineering :: Artificial Intelligence
Classifier: Topic :: Software Development
License-File: LICENSE
Requires-Dist: torch >=1.6.0
Requires-Dist: torchvision >=0.7.0
Requires-Dist: scikit-learn >=0.21.1
Requires-Dist: tqdm >=4.24.0
Requires-Dist: visdom >=0.1.8.9
Requires-Dist: numpy >=1.16.4
Requires-Dist: scipy >=1.3.1
Requires-Dist: statsmodels
Requires-Dist: platformdirs
